py2store/__init__.py
py2store/access.py
py2store/appendable.py
py2store/base.py
py2store/caching.py
py2store/core.py
py2store/dig.py
py2store/errors.py
py2store/filesys.py
py2store/misc.py
py2store/mixins.py
py2store/naming.py
py2store/parse_format.py
py2store/paths.py
py2store/signatures.py
py2store/sources.py
py2store/trans.py
py2store/util.py
py2store/examples/__init__.py
py2store/examples/dropbox_w_urllib.py
py2store/examples/kv_walking.py
py2store/examples/last_key_inserted.py
py2store/examples/python_code_stats.py
py2store/examples/write_caches.py
py2store/ext/__init__.py
py2store/ext/dataframes.py
py2store/ext/docx.py
py2store/ext/github.py
py2store/ext/gitlab.py
py2store/ext/hdf.py
py2store/ext/matlab.py
py2store/ext/wordnet.py
py2store/key_mappers/__init__.py
py2store/key_mappers/naming.py
py2store/key_mappers/paths.py
py2store/key_mappers/str_utils.py
py2store/key_mappers/tuples.py
py2store/my/__init__.py
py2store/my/grabbers.py
py2store/persisters/__init__.py
py2store/persisters/dropbox_w_dropbox.py
py2store/persisters/googledrive_w_pydrive.py
py2store/persisters/local_files.py
py2store/persisters/new_s3.py
py2store/persisters/redis_w_redis.py
py2store/persisters/s3_w_boto3.py
py2store/persisters/sql_w_sqlalchemy.py
py2store/persisters/w_aiofile.py
py2store/scrap/__init__.py
py2store/scrap/new_gen_local.py
py2store/serializers/__init__.py
py2store/serializers/jsonization.py
py2store/serializers/pickled.py
py2store/slib/__init__.py
py2store/slib/s_configparser.py
py2store/slib/s_zipfile.py
py2store/stores/__init__.py
py2store/stores/dropbox_store.py
py2store/stores/local_store.py
py2store/stores/s3_store.py
py2store/stores/sql_w_sqlalchemy.py
py2store/test/__init__.py
py2store/test/local_files_test.py
py2store/test/quick_test.py
py2store/test/scrap.py
py2store/test/util.py
py2store/utils/__init__.py
py2store/utils/affine_conversion.py
py2store/utils/appendable.py
py2store/utils/attr_dict.py
py2store/utils/cache_descriptors.py
py2store-0.0.18.dist-info/LICENSE
py2store-0.0.18.dist-info/METADATA
py2store-0.0.18.dist-info/WHEEL
py2store-0.0.18.dist-info/top_level.txt
py2store-0.0.18.dist-info/RECORD
