Metadata-Version: 2.1
Name: py2store
Version: 0.0.18
Summary: Tools to create simple and consistent interfaces to complicated and varied data sources.
Home-page: https://github.com/i2mint/py2store
Author: OtoSense
Author-email: thorwhalen1@gmail.com
License: mit
Keywords: storage,interface
Platform: any
Classifier: Intended Audience :: Developers
Classifier: Topic :: Software Development
Classifier: Programming Language :: Python :: 3.8
Requires-Dist: dol
